distributed_control_fenics/__init__.py
distributed_control_fenics/cont_obs_utils.py
distributed_control_fenics-1.0.0.dist-info/LICENSE.txt
distributed_control_fenics-1.0.0.dist-info/METADATA
distributed_control_fenics-1.0.0.dist-info/WHEEL
distributed_control_fenics-1.0.0.dist-info/top_level.txt
distributed_control_fenics-1.0.0.dist-info/RECORD
