Metadata-Version: 2.1
Name: distributed-control-fenics
Version: 1.0.0
Summary: A module of helper functions that assembles(distributed) control and observationoperators using FEniCS.
Home-page: https://github.com/highlando/distr_control_fenics
Author: Jan Heiland
Author-email: jnhlnd@gmail.com
License: MIT
Platform: UNKNOWN
Classifier: Programming Language :: Python :: 3
Classifier: Programming Language :: Python :: 2
Classifier: License :: OSI Approved :: MIT License
Requires-Dist: numpy
Requires-Dist: scipy
